{
  "/favicon.ico/route": "app/favicon.ico/route.js",
  "/page": "app/page.js",
  "/not-found": "app/not-found.js",
  "/dashboard/page": "app/dashboard/page.js",
  "/popular/page": "app/popular/page.js",
  "/blogs/page": "app/blogs/page.js",
  "/dashboard/inbox/page": "app/dashboard/inbox/page.js",
  "/dashboard/posts/page": "app/dashboard/posts/page.js",
  "/dashboard/solve/page": "app/dashboard/solve/page.js",
  "/dashboard/query/page": "app/dashboard/query/page.js",
  "/dashboard/comments/page": "app/dashboard/comments/page.js"
}